PyNeFrauds/Constructor.py
PyNeFrauds/Globals.py
PyNeFrauds/Neo4jHandler.py
PyNeFrauds/QueryConstructor.py
PyNeFrauds/__init__.py
PyNeFrauds/extractor.py
PyNeFrauds/neo4j_populator.py
PyNeFrauds/nn/EmbedFetcher.py
PyNeFrauds/nn/Evaluation.py
PyNeFrauds/nn/ModelBuilder.py
PyNeFrauds/nn/Trainer.py
PyNeFrauds/nn/__init__.py
PyNeFrauds/nn/toPyGData.py
PyNeFrauds/tests/__init__.py
PyNeFrauds/tests/tests.py
PyNeFrauds/tests/unittest_test.py
pyNeFrauds-0.0.5.dist-info/LICENSE.txt
pyNeFrauds-0.0.5.dist-info/METADATA
pyNeFrauds-0.0.5.dist-info/WHEEL
pyNeFrauds-0.0.5.dist-info/top_level.txt
pyNeFrauds-0.0.5.dist-info/RECORD
