Metadata-Version: 2.1
Name: pyNeFrauds
Version: 0.0.5
Summary: Python library that integrates with neo4j facilitating in fraud detection using deep learning techniques.
Author: Deepam Rai
License: MIT
Classifier: Programming Language :: Python :: 3
Classifier: License :: OSI Approved :: MIT License
Classifier: Operating System :: OS Independent
License-File: LICENSE.txt
Requires-Dist: matplotlib
Requires-Dist: neo4j
Requires-Dist: numpy
Requires-Dist: scikit-learn
Requires-Dist: torch
Requires-Dist: torch-geometric
